bayescoin/__init__.py
bayescoin/__main__.py
bayescoin/_cli_entry.py
bayescoin/cli.py
bayescoin/core.py
bayescoin/viz.py
bayescoin-0.1.2.dist-info/WHEEL
bayescoin-0.1.2.dist-info/entry_points.txt
bayescoin-0.1.2.dist-info/METADATA
bayescoin-0.1.2.dist-info/RECORD
