Metadata-Version: 2.3
Name: bayescoin
Version: 0.1.2
Summary: 
Author: oyghen
Author-email: oyghen <oyghen@duck.com>
Requires-Dist: matplotlib>=3.10.7
Requires-Dist: scipy>=1.16.3
Requires-Dist: typer>=0.20.0 ; extra == 'cli'
Requires-Python: >=3.11
Provides-Extra: cli
